<gallery
base = ""
background = "#FFFFFF"
banner = "#FFFFFF"
text = "#000000"
link = "#000000"
alink = "#FF0000"
vlink = "#800080"
date = "13/10/2009">
	<sitename>Christine de Pizan Gallery</sitename>
	<photographer>http://www.pizan.lib.ed.ac.uk</photographer>
	<contactinfo></contactinfo>
	<email></email>
	<security><![CDATA[]]> </security>

<banner font = "Arial" fontsize = "2" color =  "#FFFFFF"> </banner>
<thumbnail base ="thumbnails/" font = "Arial" fontsize = "5" color = "#FFFFFF" border = "0" rows = "25" col = "6"> </thumbnail> 
<large base ="images/" font = "Arial" fontsize = "2" color = "#FFFFFF" border = "0"> </large>
<images id = "images">

<image
path = "001r.jpg"
thumbpath = "001r.jpg"
thumbwidth = "143"
</image>


<image
path = "001v.jpg"
thumbpath = "001v.jpg"
thumbwidth = "143"
</image>


<image
path = "002r.jpg"
thumbpath = "002r.jpg"
thumbwidth = "143"
</image>


<image
path = "002v.jpg"
thumbpath = "002v.jpg"
thumbwidth = "144"
</image>


<image
path = "003r.jpg"
thumbpath = "003r.jpg"
thumbwidth = "143"
</image>


<image
path = "003v.jpg"
thumbpath = "003v.jpg"
thumbwidth = "144"
</image>


<image
path = "004r.jpg"
thumbpath = "004r.jpg"
thumbwidth = "143"
</image>


<image
path = "004v.jpg"
thumbpath = "004v.jpg"
thumbwidth = "143"
</image>


<image
path = "005r.jpg"
thumbpath = "005r.jpg"
thumbwidth = "143"
</image>


<image
path = "005v.jpg"
thumbpath = "005v.jpg"
thumbwidth = "144"
</image>


<image
path = "006r.jpg"
thumbpath = "006r.jpg"
thumbwidth = "143"
</image>


<image
path = "006v.jpg"
thumbpath = "006v.jpg"
thumbwidth = "143"
</image>


<image
path = "007r.jpg"
thumbpath = "007r.jpg"
thumbwidth = "143"
</image>


<image
path = "007v.jpg"
thumbpath = "007v.jpg"
thumbwidth = "144"
</image>


<image
path = "008r.jpg"
thumbpath = "008r.jpg"
thumbwidth = "143"
</image>


<image
path = "008v.jpg"
thumbpath = "008v.jpg"
thumbwidth = "143"
</image>


<image
path = "009r.jpg"
thumbpath = "009r.jpg"
thumbwidth = "143"
</image>


<image
path = "009v.jpg"
thumbpath = "009v.jpg"
thumbwidth = "143"
</image>


<image
path = "010r.jpg"
thumbpath = "010r.jpg"
thumbwidth = "142"
</image>


<image
path = "010v.jpg"
thumbpath = "010v.jpg"
thumbwidth = "142"
</image>


<image
path = "011r.jpg"
thumbpath = "011r.jpg"
thumbwidth = "142"
</image>


<image
path = "011v.jpg"
thumbpath = "011v.jpg"
thumbwidth = "143"
</image>


<image
path = "012r.jpg"
thumbpath = "012r.jpg"
thumbwidth = "142"
</image>


<image
path = "012v.jpg"
thumbpath = "012v.jpg"
thumbwidth = "142"
</image>


<image
path = "013r.jpg"
thumbpath = "013r.jpg"
thumbwidth = "143"
</image>


<image
path = "013v.jpg"
thumbpath = "013v.jpg"
thumbwidth = "143"
</image>


<image
path = "014r.jpg"
thumbpath = "014r.jpg"
thumbwidth = "142"
</image>


<image
path = "014v.jpg"
thumbpath = "014v.jpg"
thumbwidth = "143"
</image>


<image
path = "015r.jpg"
thumbpath = "015r.jpg"
thumbwidth = "143"
</image>


<image
path = "015v.jpg"
thumbpath = "015v.jpg"
thumbwidth = "143"
</image>


<image
path = "016r.jpg"
thumbpath = "016r.jpg"
thumbwidth = "142"
</image>


<image
path = "016v.jpg"
thumbpath = "016v.jpg"
thumbwidth = "143"
</image>


<image
path = "017r.jpg"
thumbpath = "017r.jpg"
thumbwidth = "142"
</image>


<image
path = "017v.jpg"
thumbpath = "017v.jpg"
thumbwidth = "142"
</image>


<image
path = "018r.jpg"
thumbpath = "018r.jpg"
thumbwidth = "143"
</image>


<image
path = "018v.jpg"
thumbpath = "018v.jpg"
thumbwidth = "143"
</image>


<image
path = "019r.jpg"
thumbpath = "019r.jpg"
thumbwidth = "143"
</image>


<image
path = "019v.jpg"
thumbpath = "019v.jpg"
thumbwidth = "143"
</image>


<image
path = "020r.jpg"
thumbpath = "020r.jpg"
thumbwidth = "143"
</image>


<image
path = "020v.jpg"
thumbpath = "020v.jpg"
thumbwidth = "144"
</image>


<image
path = "021r.jpg"
thumbpath = "021r.jpg"
thumbwidth = "143"
</image>


<image
path = "021v.jpg"
thumbpath = "021v.jpg"
thumbwidth = "143"
</image>


<image
path = "022r.jpg"
thumbpath = "022r.jpg"
thumbwidth = "142"
</image>


<image
path = "022v.jpg"
thumbpath = "022v.jpg"
thumbwidth = "143"
</image>


<image
path = "023r.jpg"
thumbpath = "023r.jpg"
thumbwidth = "142"
</image>


<image
path = "023v.jpg"
thumbpath = "023v.jpg"
thumbwidth = "143"
</image>


<image
path = "024r.jpg"
thumbpath = "024r.jpg"
thumbwidth = "143"
</image>


<image
path = "024v.jpg"
thumbpath = "024v.jpg"
thumbwidth = "143"
</image>


<image
path = "025r.jpg"
thumbpath = "025r.jpg"
thumbwidth = "143"
</image>


<image
path = "025v.jpg"
thumbpath = "025v.jpg"
thumbwidth = "143"
</image>


<image
path = "026r.jpg"
thumbpath = "026r.jpg"
thumbwidth = "153"
</image>


<image
path = "026v.jpg"
thumbpath = "026v.jpg"
thumbwidth = "154"
</image>


<image
path = "027r.jpg"
thumbpath = "027r.jpg"
thumbwidth = "140"
</image>


<image
path = "027v.jpg"
thumbpath = "027v.jpg"
thumbwidth = "154"
</image>


<image
path = "028r.jpg"
thumbpath = "028r.jpg"
thumbwidth = "150"
</image>


<image
path = "028v.jpg"
thumbpath = "028v.jpg"
thumbwidth = "142"
</image>


<image
path = "029r.jpg"
thumbpath = "029r.jpg"
thumbwidth = "143"
</image>


<image
path = "029v.jpg"
thumbpath = "029v.jpg"
thumbwidth = "143"
</image>


<image
path = "030r.jpg"
thumbpath = "030r.jpg"
thumbwidth = "141"
</image>


<image
path = "030v.jpg"
thumbpath = "030v.jpg"
thumbwidth = "149"
</image>


<image
path = "031r.jpg"
thumbpath = "031r.jpg"
thumbwidth = "141"
</image>


<image
path = "031v.jpg"
thumbpath = "031v.jpg"
thumbwidth = "149"
</image>


<image
path = "032r.jpg"
thumbpath = "032r.jpg"
thumbwidth = "143"
</image>


<image
path = "032v.jpg"
thumbpath = "032v.jpg"
thumbwidth = "144"
</image>


<image
path = "033r.jpg"
thumbpath = "033r.jpg"
thumbwidth = "144"
</image>


<image
path = "033v.jpg"
thumbpath = "033v.jpg"
thumbwidth = "143"
</image>


<image
path = "034r.jpg"
thumbpath = "034r.jpg"
thumbwidth = "142"
</image>


<image
path = "034v.jpg"
thumbpath = "034v.jpg"
thumbwidth = "145"
</image>


<image
path = "035r.jpg"
thumbpath = "035r.jpg"
thumbwidth = "145"
</image>


<image
path = "035v.jpg"
thumbpath = "035v.jpg"
thumbwidth = "143"
</image>


<image
path = "036r.jpg"
thumbpath = "036r.jpg"
thumbwidth = "146"
</image>


<image
path = "036v.jpg"
thumbpath = "036v.jpg"
thumbwidth = "147"
</image>


<image
path = "037r.jpg"
thumbpath = "037r.jpg"
thumbwidth = "142"
</image>


<image
path = "037v.jpg"
thumbpath = "037v.jpg"
thumbwidth = "145"
</image>


<image
path = "038r.jpg"
thumbpath = "038r.jpg"
thumbwidth = "145"
</image>


<image
path = "038v.jpg"
thumbpath = "038v.jpg"
thumbwidth = "145"
</image>


<image
path = "039r.jpg"
thumbpath = "039r.jpg"
thumbwidth = "146"
</image>


<image
path = "039v.jpg"
thumbpath = "039v.jpg"
thumbwidth = "141"
</image>


<image
path = "040r.jpg"
thumbpath = "040r.jpg"
thumbwidth = "146"
</image>


<image
path = "040v.jpg"
thumbpath = "040v.jpg"
thumbwidth = "141"
</image>


<image
path = "041r.jpg"
thumbpath = "041r.jpg"
thumbwidth = "141"
</image>


<image
path = "041v.jpg"
thumbpath = "041v.jpg"
thumbwidth = "143"
</image>


<image
path = "042r.jpg"
thumbpath = "042r.jpg"
thumbwidth = "141"
</image>


<image
path = "042v.jpg"
thumbpath = "042v.jpg"
thumbwidth = "141"
</image>


<image
path = "043r.jpg"
thumbpath = "043r.jpg"
thumbwidth = "142"
</image>


<image
path = "043v.jpg"
thumbpath = "043v.jpg"
thumbwidth = "141"
</image>


<image
path = "044r.jpg"
thumbpath = "044r.jpg"
thumbwidth = "141"
</image>


<image
path = "044v.jpg"
thumbpath = "044v.jpg"
thumbwidth = "143"
</image>


<image
path = "045r.jpg"
thumbpath = "045r.jpg"
thumbwidth = "141"
</image>


<image
path = "045v.jpg"
thumbpath = "045v.jpg"
thumbwidth = "143"
</image>


<image
path = "046r.jpg"
thumbpath = "046r.jpg"
thumbwidth = "143"
</image>


<image
path = "046v.jpg"
thumbpath = "046v.jpg"
thumbwidth = "142"
</image>


<image
path = "047r.jpg"
thumbpath = "047r.jpg"
thumbwidth = "142"
</image>


<image
path = "047v.jpg"
thumbpath = "047v.jpg"
thumbwidth = "142"
</image>


<image
path = "048r.jpg"
thumbpath = "048r.jpg"
thumbwidth = "143"
</image>


<image
path = "048v.jpg"
thumbpath = "048v.jpg"
thumbwidth = "142"
</image>


<image
path = "049r.jpg"
thumbpath = "049r.jpg"
thumbwidth = "141"
</image>


<image
path = "049v.jpg"
thumbpath = "049v.jpg"
thumbwidth = "142"
</image>


<image
path = "050r.jpg"
thumbpath = "050r.jpg"
thumbwidth = "143"
</image>


<image
path = "050v.jpg"
thumbpath = "050v.jpg"
thumbwidth = "143"
</image>


<image
path = "051r.jpg"
thumbpath = "051r.jpg"
thumbwidth = "143"
</image>


<image
path = "051v.jpg"
thumbpath = "051v.jpg"
thumbwidth = "140"
</image>


<image
path = "052r.jpg"
thumbpath = "052r.jpg"
thumbwidth = "140"
</image>


<image
path = "052v.jpg"
thumbpath = "052v.jpg"
thumbwidth = "138"
</image>


<image
path = "053r.jpg"
thumbpath = "053r.jpg"
thumbwidth = "140"
</image>


<image
path = "053v.jpg"
thumbpath = "053v.jpg"
thumbwidth = "138"
</image>


<image
path = "054r.jpg"
thumbpath = "054r.jpg"
thumbwidth = "139"
</image>


<image
path = "054v.jpg"
thumbpath = "054v.jpg"
thumbwidth = "139"
</image>


<image
path = "055r.jpg"
thumbpath = "055r.jpg"
thumbwidth = "139"
</image>


<image
path = "055v.jpg"
thumbpath = "055v.jpg"
thumbwidth = "139"
</image>


<image
path = "056r.jpg"
thumbpath = "056r.jpg"
thumbwidth = "139"
</image>


<image
path = "056v.jpg"
thumbpath = "056v.jpg"
thumbwidth = "139"
</image>


<image
path = "057r.jpg"
thumbpath = "057r.jpg"
thumbwidth = "139"
</image>


<image
path = "057v.jpg"
thumbpath = "057v.jpg"
thumbwidth = "140"
</image>


<image
path = "058r.jpg"
thumbpath = "058r.jpg"
thumbwidth = "138"
</image>


<image
path = "058v.jpg"
thumbpath = "058v.jpg"
thumbwidth = "139"
</image>


<image
path = "059r.jpg"
thumbpath = "059r.jpg"
thumbwidth = "138"
</image>


<image
path = "059v.jpg"
thumbpath = "059v.jpg"
thumbwidth = "139"
</image>


<image
path = "060r.jpg"
thumbpath = "060r.jpg"
thumbwidth = "139"
</image>


<image
path = "060v.jpg"
thumbpath = "060v.jpg"
thumbwidth = "139"
</image>


<image
path = "061r.jpg"
thumbpath = "061r.jpg"
thumbwidth = "138"
</image>


<image
path = "061v.jpg"
thumbpath = "061v.jpg"
thumbwidth = "139"
</image>


<image
path = "062r.jpg"
thumbpath = "062r.jpg"
thumbwidth = "139"
</image>


<image
path = "062v.jpg"
thumbpath = "062v.jpg"
thumbwidth = "138"
</image>


<image
path = "063r.jpg"
thumbpath = "063r.jpg"
thumbwidth = "139"
</image>


<image
path = "063v.jpg"
thumbpath = "063v.jpg"
thumbwidth = "139"
</image>


<image
path = "064r.jpg"
thumbpath = "064r.jpg"
thumbwidth = "139"
</image>


<image
path = "064v.jpg"
thumbpath = "064v.jpg"
thumbwidth = "138"
</image>


<image
path = "065r.jpg"
thumbpath = "065r.jpg"
thumbwidth = "139"
</image>


<image
path = "065v.jpg"
thumbpath = "065v.jpg"
thumbwidth = "140"
</image>


<image
path = "066r.jpg"
thumbpath = "066r.jpg"
thumbwidth = "140"
</image>


<image
path = "066v.jpg"
thumbpath = "066v.jpg"
thumbwidth = "139"
</image>


<image
path = "067r.jpg"
thumbpath = "067r.jpg"
thumbwidth = "140"
</image>


<image
path = "067v.jpg"
thumbpath = "067v.jpg"
thumbwidth = "139"
</image>


<image
path = "068r.jpg"
thumbpath = "068r.jpg"
thumbwidth = "138"
</image>


<image
path = "068v.jpg"
thumbpath = "068v.jpg"
thumbwidth = "140"
</image>


<image
path = "069r.jpg"
thumbpath = "069r.jpg"
thumbwidth = "139"
</image>


<image
path = "069v.jpg"
thumbpath = "069v.jpg"
thumbwidth = "143"
</image>


<image
path = "070r.jpg"
thumbpath = "070r.jpg"
thumbwidth = "139"
</image>


<image
path = "070v.jpg"
thumbpath = "070v.jpg"
thumbwidth = "139"
</image>


<image
path = "071r.jpg"
thumbpath = "071r.jpg"
thumbwidth = "140"
</image>


<image
path = "071v.jpg"
thumbpath = "071v.jpg"
thumbwidth = "138"
</image>


<image
path = "072r.jpg"
thumbpath = "072r.jpg"
thumbwidth = "139"
</image>


<image
path = "072v.jpg"
thumbpath = "072v.jpg"
thumbwidth = "138"
</image>


<image
path = "073r.jpg"
thumbpath = "073r.jpg"
thumbwidth = "138"
</image>


<image
path = "073v.jpg"
thumbpath = "073v.jpg"
thumbwidth = "138"
</image>


<image
path = "074r.jpg"
thumbpath = "074r.jpg"
thumbwidth = "139"
</image>


<image
path = "074v.jpg"
thumbpath = "074v.jpg"
thumbwidth = "139"
</image>


<image
path = "075r.jpg"
thumbpath = "075r.jpg"
thumbwidth = "139"
</image>


<image
path = "075v.jpg"
thumbpath = "075v.jpg"
thumbwidth = "139"
</image>


<image
path = "076r.jpg"
thumbpath = "076r.jpg"
thumbwidth = "139"
</image>


<image
path = "076v.jpg"
thumbpath = "076v.jpg"
thumbwidth = "139"
</image>


<image
path = "077r.jpg"
thumbpath = "077r.jpg"
thumbwidth = "139"
</image>


<image
path = "077v.jpg"
thumbpath = "077v.jpg"
thumbwidth = "139"
</image>


<image
path = "078r.jpg"
thumbpath = "078r.jpg"
thumbwidth = "139"
</image>


<image
path = "078v.jpg"
thumbpath = "078v.jpg"
thumbwidth = "139"
</image>


<image
path = "079r.jpg"
thumbpath = "079r.jpg"
thumbwidth = "140"
</image>


<image
path = "079v.jpg"
thumbpath = "079v.jpg"
thumbwidth = "140"
</image>


<image
path = "080r.jpg"
thumbpath = "080r.jpg"
thumbwidth = "139"
</image>


<image
path = "080v.jpg"
thumbpath = "080v.jpg"
thumbwidth = "139"
</image>


<image
path = "081r.jpg"
thumbpath = "081r.jpg"
thumbwidth = "139"
</image>


<image
path = "081v.jpg"
thumbpath = "081v.jpg"
thumbwidth = "139"
</image>


<image
path = "082r.jpg"
thumbpath = "082r.jpg"
thumbwidth = "139"
</image>


<image
path = "082v.jpg"
thumbpath = "082v.jpg"
thumbwidth = "140"
</image>


<image
path = "083r.jpg"
thumbpath = "083r.jpg"
thumbwidth = "139"
</image>


<image
path = "083v.jpg"
thumbpath = "083v.jpg"
thumbwidth = "139"
</image>


<image
path = "084r.jpg"
thumbpath = "084r.jpg"
thumbwidth = "141"
</image>


<image
path = "084v.jpg"
thumbpath = "084v.jpg"
thumbwidth = "139"
</image>


<image
path = "085r.jpg"
thumbpath = "085r.jpg"
thumbwidth = "139"
</image>


<image
path = "085v.jpg"
thumbpath = "085v.jpg"
thumbwidth = "140"
</image>


<image
path = "086r.jpg"
thumbpath = "086r.jpg"
thumbwidth = "139"
</image>


<image
path = "086v.jpg"
thumbpath = "086v.jpg"
thumbwidth = "140"
</image>


<image
path = "087r.jpg"
thumbpath = "087r.jpg"
thumbwidth = "141"
</image>


<image
path = "087v.jpg"
thumbpath = "087v.jpg"
thumbwidth = "145"
</image>


<image
path = "088r.jpg"
thumbpath = "088r.jpg"
thumbwidth = "145"
</image>


<image
path = "088v.jpg"
thumbpath = "088v.jpg"
thumbwidth = "145"
</image>


<image
path = "089r.jpg"
thumbpath = "089r.jpg"
thumbwidth = "141"
</image>


<image
path = "089v.jpg"
thumbpath = "089v.jpg"
thumbwidth = "145"
</image>


<image
path = "090r.jpg"
thumbpath = "090r.jpg"
thumbwidth = "145"
</image>


<image
path = "090v.jpg"
thumbpath = "090v.jpg"
thumbwidth = "145"
</image>


<image
path = "091r.jpg"
thumbpath = "091r.jpg"
thumbwidth = "146"
</image>


<image
path = "091v.jpg"
thumbpath = "091v.jpg"
thumbwidth = "145"
</image>


<image
path = "092r.jpg"
thumbpath = "092r.jpg"
thumbwidth = "145"
</image>


<image
path = "092v.jpg"
thumbpath = "092v.jpg"
thumbwidth = "141"
</image>


<image
path = "093r.jpg"
thumbpath = "093r.jpg"
thumbwidth = "146"
</image>


<image
path = "093v.jpg"
thumbpath = "093v.jpg"
thumbwidth = "145"
</image>


<image
path = "094r.jpg"
thumbpath = "094r.jpg"
thumbwidth = "140"
</image>


<image
path = "094v.jpg"
thumbpath = "094v.jpg"
thumbwidth = "146"
</image>


<image
path = "095r.jpg"
thumbpath = "095r.jpg"
thumbwidth = "144"
</image>


<image
path = "095v.jpg"
thumbpath = "095v.jpg"
thumbwidth = "143"
</image>


<image
path = "096r.jpg"
thumbpath = "096r.jpg"
thumbwidth = "145"
</image>


<image
path = "096v.jpg"
thumbpath = "096v.jpg"
thumbwidth = "146"
</image>


<image
path = "097r.jpg"
thumbpath = "097r.jpg"
thumbwidth = "141"
</image>


<image
path = "097v.jpg"
thumbpath = "097v.jpg"
thumbwidth = "146"
</image>


<image
path = "098r.jpg"
thumbpath = "098r.jpg"
thumbwidth = "146"
</image>


<image
path = "098v.jpg"
thumbpath = "098v.jpg"
thumbwidth = "140"
</image>


<image
path = "099r.jpg"
thumbpath = "099r.jpg"
thumbwidth = "146"
</image>


<image
path = "099v.jpg"
thumbpath = "099v.jpg"
thumbwidth = "145"
</image>


<image
path = "100r.jpg"
thumbpath = "100r.jpg"
thumbwidth = "145"
</image>


<image
path = "100v.jpg"
thumbpath = "100v.jpg"
thumbwidth = "141"
</image>


<image
path = "101r.jpg"
thumbpath = "101r.jpg"
thumbwidth = "145"
</image>


<image
path = "101v.jpg"
thumbpath = "101v.jpg"
thumbwidth = "146"
</image>


<image
path = "102r.jpg"
thumbpath = "102r.jpg"
thumbwidth = "145"
</image>


<image
path = "102v.jpg"
thumbpath = "102v.jpg"
thumbwidth = "141"
</image>


<image
path = "103r.jpg"
thumbpath = "103r.jpg"
thumbwidth = "146"
</image>


<image
path = "103v.jpg"
thumbpath = "103v.jpg"
thumbwidth = "140"
</image>


<image
path = "104r.jpg"
thumbpath = "104r.jpg"
thumbwidth = "145"
</image>


<image
path = "104v.jpg"
thumbpath = "104v.jpg"
thumbwidth = "140"
</image>


<image
path = "105r.jpg"
thumbpath = "105r.jpg"
thumbwidth = "143"
</image>


<image
path = "105v.jpg"
thumbpath = "105v.jpg"
thumbwidth = "145"
</image>


<image
path = "106r.jpg"
thumbpath = "106r.jpg"
thumbwidth = "141"
</image>


<image
path = "106v.jpg"
thumbpath = "106v.jpg"
thumbwidth = "141"
</image>


<image
path = "107r.jpg"
thumbpath = "107r.jpg"
thumbwidth = "145"
</image>


<image
path = "107v.jpg"
thumbpath = "107v.jpg"
thumbwidth = "140"
</image>


<image
path = "108r.jpg"
thumbpath = "108r.jpg"
thumbwidth = "141"
</image>


<image
path = "108v.jpg"
thumbpath = "108v.jpg"
thumbwidth = "141"
</image>


<image
path = "109r.jpg"
thumbpath = "109r.jpg"
thumbwidth = "142"
</image>


<image
path = "109v.jpg"
thumbpath = "109v.jpg"
thumbwidth = "139"
</image>


<image
path = "110r.jpg"
thumbpath = "110r.jpg"
thumbwidth = "138"
</image>


<image
path = "110v.jpg"
thumbpath = "110v.jpg"
thumbwidth = "139"
</image>


<image
path = "111r.jpg"
thumbpath = "111r.jpg"
thumbwidth = "141"
</image>


<image
path = "111v.jpg"
thumbpath = "111v.jpg"
thumbwidth = "139"
</image>


<image
path = "112r.jpg"
thumbpath = "112r.jpg"
thumbwidth = "139"
</image>


<image
path = "112v.jpg"
thumbpath = "112v.jpg"
thumbwidth = "139"
</image>


<image
path = "113r.jpg"
thumbpath = "113r.jpg"
thumbwidth = "138"
</image>


<image
path = "113v.jpg"
thumbpath = "113v.jpg"
thumbwidth = "138"
</image>


<image
path = "114r.jpg"
thumbpath = "114r.jpg"
thumbwidth = "138"
</image>


<image
path = "114v.jpg"
thumbpath = "114v.jpg"
thumbwidth = "139"
</image>


<image
path = "115r.jpg"
thumbpath = "115r.jpg"
thumbwidth = "139"
</image>


<image
path = "115v.jpg"
thumbpath = "115v.jpg"
thumbwidth = "140"
</image>


<image
path = "116r.jpg"
thumbpath = "116r.jpg"
thumbwidth = "138"
</image>


<image
path = "116v.jpg"
thumbpath = "116v.jpg"
thumbwidth = "139"
</image>


<image
path = "117r.jpg"
thumbpath = "117r.jpg"
thumbwidth = "139"
</image>


<image
path = "117v.jpg"
thumbpath = "117v.jpg"
thumbwidth = "138"
</image>


<image
path = "118r.jpg"
thumbpath = "118r.jpg"
thumbwidth = "138"
</image>


<image
path = "118v.jpg"
thumbpath = "118v.jpg"
thumbwidth = "139"
</image>


<image
path = "119r.jpg"
thumbpath = "119r.jpg"
thumbwidth = "138"
</image>


<image
path = "119v.jpg"
thumbpath = "119v.jpg"
thumbwidth = "140"
</image>


<image
path = "120r.jpg"
thumbpath = "120r.jpg"
thumbwidth = "139"
</image>


<image
path = "120v.jpg"
thumbpath = "120v.jpg"
thumbwidth = "140"
</image>


<image
path = "121r.jpg"
thumbpath = "121r.jpg"
thumbwidth = "141"
</image>


<image
path = "121v.jpg"
thumbpath = "121v.jpg"
thumbwidth = "139"
</image>


<image
path = "122r.jpg"
thumbpath = "122r.jpg"
thumbwidth = "140"
</image>


<image
path = "122v.jpg"
thumbpath = "122v.jpg"
thumbwidth = "139"
</image>


<image
path = "123r.jpg"
thumbpath = "123r.jpg"
thumbwidth = "138"
</image>


<image
path = "123v.jpg"
thumbpath = "123v.jpg"
thumbwidth = "144"
</image>


<image
path = "124r.jpg"
thumbpath = "124r.jpg"
thumbwidth = "139"
</image>


<image
path = "124v.jpg"
thumbpath = "124v.jpg"
thumbwidth = "139"
</image>


<image
path = "125r.jpg"
thumbpath = "125r.jpg"
thumbwidth = "139"
</image>


<image
path = "125v.jpg"
thumbpath = "125v.jpg"
thumbwidth = "140"
</image>


<image
path = "126r.jpg"
thumbpath = "126r.jpg"
thumbwidth = "140"
</image>


<image
path = "126v.jpg"
thumbpath = "126v.jpg"
thumbwidth = "142"
</image>


<image
path = "127r.jpg"
thumbpath = "127r.jpg"
thumbwidth = "141"
</image>


<image
path = "127v.jpg"
thumbpath = "127v.jpg"
thumbwidth = "140"
</image>


<image
path = "128r.jpg"
thumbpath = "128r.jpg"
thumbwidth = "141"
</image>


<image
path = "128v.jpg"
thumbpath = "128v.jpg"
thumbwidth = "140"
</image>


<image
path = "129r.jpg"
thumbpath = "129r.jpg"
thumbwidth = "141"
</image>


<image
path = "129v.jpg"
thumbpath = "129v.jpg"
thumbwidth = "141"
</image>


<image
path = "130r.jpg"
thumbpath = "130r.jpg"
thumbwidth = "141"
</image>


<image
path = "130v.jpg"
thumbpath = "130v.jpg"
thumbwidth = "140"
</image>


<image
path = "131r.jpg"
thumbpath = "131r.jpg"
thumbwidth = "141"
</image>


<image
path = "131v.jpg"
thumbpath = "131v.jpg"
thumbwidth = "140"
</image>


<image
path = "132r.jpg"
thumbpath = "132r.jpg"
thumbwidth = "140"
</image>


<image
path = "132v.jpg"
thumbpath = "132v.jpg"
thumbwidth = "140"
</image>


<image
path = "133r.jpg"
thumbpath = "133r.jpg"
thumbwidth = "140"
</image>


<image
path = "133v.jpg"
thumbpath = "133v.jpg"
thumbwidth = "139"
</image>


<image
path = "134r.jpg"
thumbpath = "134r.jpg"
thumbwidth = "140"
</image>


<image
path = "134v.jpg"
thumbpath = "134v.jpg"
thumbwidth = "139"
</image>


<image
path = "135r.jpg"
thumbpath = "135r.jpg"
thumbwidth = "140"
</image>


<image
path = "135v.jpg"
thumbpath = "135v.jpg"
thumbwidth = "140"
</image>


<image
path = "136r.jpg"
thumbpath = "136r.jpg"
thumbwidth = "140"
</image>


<image
path = "136v.jpg"
thumbpath = "136v.jpg"
thumbwidth = "140"
</image>


<image
path = "137r.jpg"
thumbpath = "137r.jpg"
thumbwidth = "140"
</image>


<image
path = "137v.jpg"
thumbpath = "137v.jpg"
thumbwidth = "140"
</image>


<image
path = "138r.jpg"
thumbpath = "138r.jpg"
thumbwidth = "140"
</image>


<image
path = "138v.jpg"
thumbpath = "138v.jpg"
thumbwidth = "139"
</image>


<image
path = "139r.jpg"
thumbpath = "139r.jpg"
thumbwidth = "141"
</image>


<image
path = "139v.jpg"
thumbpath = "139v.jpg"
thumbwidth = "140"
</image>


<image
path = "140r.jpg"
thumbpath = "140r.jpg"
thumbwidth = "140"
</image>


<image
path = "140v.jpg"
thumbpath = "140v.jpg"
thumbwidth = "138"
</image>


<image
path = "141r.jpg"
thumbpath = "141r.jpg"
thumbwidth = "141"
</image>


<image
path = "141v.jpg"
thumbpath = "141v.jpg"
thumbwidth = "139"
</image>


<image
path = "142r.jpg"
thumbpath = "142r.jpg"
thumbwidth = "139"
</image>


<image
path = "142v.jpg"
thumbpath = "142v.jpg"
thumbwidth = "139"
</image>


<image
path = "143r.jpg"
thumbpath = "143r.jpg"
thumbwidth = "143"
</image>


<image
path = "143v.jpg"
thumbpath = "143v.jpg"
thumbwidth = "139"
</image>


<image
path = "144r.jpg"
thumbpath = "144r.jpg"
thumbwidth = "140"
</image>


<image
path = "144v.jpg"
thumbpath = "144v.jpg"
thumbwidth = "138"
</image>


<image
path = "145r.jpg"
thumbpath = "145r.jpg"
thumbwidth = "140"
</image>


<image
path = "145v.jpg"
thumbpath = "145v.jpg"
thumbwidth = "139"
</image>


<image
path = "146r.jpg"
thumbpath = "146r.jpg"
thumbwidth = "139"
</image>


<image
path = "146v.jpg"
thumbpath = "146v.jpg"
thumbwidth = "141"
</image>


<image
path = "147r.jpg"
thumbpath = "147r.jpg"
thumbwidth = "141"
</image>


<image
path = "147v.jpg"
thumbpath = "147v.jpg"
thumbwidth = "141"
</image>


<image
path = "148r.jpg"
thumbpath = "148r.jpg"
thumbwidth = "141"
</image>


<image
path = "148v.jpg"
thumbpath = "148v.jpg"
thumbwidth = "141"
</image>


<image
path = "149r.jpg"
thumbpath = "149r.jpg"
thumbwidth = "143"
</image>


<image
path = "149v.jpg"
thumbpath = "149v.jpg"
thumbwidth = "143"
</image>


<image
path = "150r.jpg"
thumbpath = "150r.jpg"
thumbwidth = "143"
</image>


<image
path = "150v.jpg"
thumbpath = "150v.jpg"
thumbwidth = "144"
</image>


<image
path = "151r.jpg"
thumbpath = "151r.jpg"
thumbwidth = "143"
</image>


<image
path = "151v.jpg"
thumbpath = "151v.jpg"
thumbwidth = "144"
</image>


<image
path = "152r.jpg"
thumbpath = "152r.jpg"
thumbwidth = "144"
</image>


<image
path = "152v.jpg"
thumbpath = "152v.jpg"
thumbwidth = "144"
</image>


<image
path = "153r.jpg"
thumbpath = "153r.jpg"
thumbwidth = "144"
</image>


<image
path = "153v.jpg"
thumbpath = "153v.jpg"
thumbwidth = "144"
</image>


<image
path = "154r.jpg"
thumbpath = "154r.jpg"
thumbwidth = "144"
</image>


<image
path = "154v.jpg"
thumbpath = "154v.jpg"
thumbwidth = "144"
</image>


<image
path = "155r.jpg"
thumbpath = "155r.jpg"
thumbwidth = "144"
</image>


<image
path = "155v.jpg"
thumbpath = "155v.jpg"
thumbwidth = "144"
</image>


<image
path = "156r.jpg"
thumbpath = "156r.jpg"
thumbwidth = "144"
</image>


<image
path = "156v.jpg"
thumbpath = "156v.jpg"
thumbwidth = "144"
</image>


<image
path = "157r.jpg"
thumbpath = "157r.jpg"
thumbwidth = "144"
</image>


<image
path = "157v.jpg"
thumbpath = "157v.jpg"
thumbwidth = "144"
</image>


<image
path = "158r.jpg"
thumbpath = "158r.jpg"
thumbwidth = "144"
</image>


<image
path = "158v.jpg"
thumbpath = "158v.jpg"
thumbwidth = "144"
</image>


<image
path = "159r.jpg"
thumbpath = "159r.jpg"
thumbwidth = "144"
</image>


<image
path = "159v.jpg"
thumbpath = "159v.jpg"
thumbwidth = "144"
</image>


<image
path = "160r.jpg"
thumbpath = "160r.jpg"
thumbwidth = "141"
</image>


<image
path = "160v.jpg"
thumbpath = "160v.jpg"
thumbwidth = "144"
</image>


<image
path = "161r.jpg"
thumbpath = "161r.jpg"
thumbwidth = "144"
</image>


<image
path = "161v.jpg"
thumbpath = "161v.jpg"
thumbwidth = "144"
</image>


<image
path = "162r.jpg"
thumbpath = "162r.jpg"
thumbwidth = "144"
</image>


<image
path = "162v.jpg"
thumbpath = "162v.jpg"
thumbwidth = "141"
</image>


<image
path = "163r.jpg"
thumbpath = "163r.jpg"
thumbwidth = "141"
</image>


<image
path = "163v.jpg"
thumbpath = "163v.jpg"
thumbwidth = "141"
</image>


<image
path = "164r.jpg"
thumbpath = "164r.jpg"
thumbwidth = "141"
</image>


<image
path = "164v.jpg"
thumbpath = "164v.jpg"
thumbwidth = "141"
</image>


<image
path = "165r.jpg"
thumbpath = "165r.jpg"
thumbwidth = "141"
</image>


<image
path = "165v.jpg"
thumbpath = "165v.jpg"
thumbwidth = "141"
</image>


<image
path = "166r.jpg"
thumbpath = "166r.jpg"
thumbwidth = "141"
</image>


<image
path = "166v.jpg"
thumbpath = "166v.jpg"
thumbwidth = "141"
</image>


<image
path = "167r.jpg"
thumbpath = "167r.jpg"
thumbwidth = "143"
</image>


<image
path = "167v.jpg"
thumbpath = "167v.jpg"
thumbwidth = "141"
</image>


<image
path = "168r.jpg"
thumbpath = "168r.jpg"
thumbwidth = "141"
</image>


<image
path = "168v.jpg"
thumbpath = "168v.jpg"
thumbwidth = "141"
</image>


<image
path = "169r.jpg"
thumbpath = "169r.jpg"
thumbwidth = "141"
</image>


<image
path = "169v.jpg"
thumbpath = "169v.jpg"
thumbwidth = "141"
</image>


<image
path = "170r.jpg"
thumbpath = "170r.jpg"
thumbwidth = "141"
</image>


<image
path = "170v.jpg"
thumbpath = "170v.jpg"
thumbwidth = "141"
</image>


<image
path = "171r.jpg"
thumbpath = "171r.jpg"
thumbwidth = "141"
</image>


<image
path = "171v.jpg"
thumbpath = "171v.jpg"
thumbwidth = "141"
</image>


<image
path = "172r.jpg"
thumbpath = "172r.jpg"
thumbwidth = "141"
</image>


<image
path = "172v.jpg"
thumbpath = "172v.jpg"
thumbwidth = "141"
</image>


<image
path = "173r.jpg"
thumbpath = "173r.jpg"
thumbwidth = "141"
</image>


<image
path = "173v.jpg"
thumbpath = "173v.jpg"
thumbwidth = "141"
</image>


<image
path = "174r.jpg"
thumbpath = "174r.jpg"
thumbwidth = "142"
</image>


<image
path = "174v.jpg"
thumbpath = "174v.jpg"
thumbwidth = "145"
</image>


<image
path = "175r.jpg"
thumbpath = "175r.jpg"
thumbwidth = "145"
</image>


<image
path = "175v.jpg"
thumbpath = "175v.jpg"
thumbwidth = "138"
</image>


<image
path = "176r.jpg"
thumbpath = "176r.jpg"
thumbwidth = "146"
</image>


<image
path = "176v.jpg"
thumbpath = "176v.jpg"
thumbwidth = "138"
</image>


<image
path = "177r.jpg"
thumbpath = "177r.jpg"
thumbwidth = "146"
</image>


<image
path = "177v.jpg"
thumbpath = "177v.jpg"
thumbwidth = "138"
</image>


<image
path = "178r.jpg"
thumbpath = "178r.jpg"
thumbwidth = "145"
</image>


<image
path = "178v.jpg"
thumbpath = "178v.jpg"
thumbwidth = "145"
</image>


<image
path = "179r.jpg"
thumbpath = "179r.jpg"
thumbwidth = "146"
</image>


<image
path = "179v.jpg"
thumbpath = "179v.jpg"
thumbwidth = "146"
</image>


<image
path = "180r.jpg"
thumbpath = "180r.jpg"
thumbwidth = "141"
</image>


<image
path = "180v.jpg"
thumbpath = "180v.jpg"
thumbwidth = "145"
</image>


<image
path = "181r.jpg"
thumbpath = "181r.jpg"
thumbwidth = "145"
</image>


<image
path = "181v.jpg"
thumbpath = "181v.jpg"
thumbwidth = "146"
</image>


<image
path = "182r.jpg"
thumbpath = "182r.jpg"
thumbwidth = "146"
</image>


<image
path = "182v.jpg"
thumbpath = "182v.jpg"
thumbwidth = "145"
</image>


<image
path = "183r.jpg"
thumbpath = "183r.jpg"
thumbwidth = "145"
</image>


<image
path = "183v.jpg"
thumbpath = "183v.jpg"
thumbwidth = "147"
</image>


<image
path = "184r.jpg"
thumbpath = "184r.jpg"
thumbwidth = "145"
</image>


<image
path = "184v.jpg"
thumbpath = "184v.jpg"
thumbwidth = "145"
</image>


<image
path = "185r.jpg"
thumbpath = "185r.jpg"
thumbwidth = "146"
</image>


<image
path = "185v.jpg"
thumbpath = "185v.jpg"
thumbwidth = "145"
</image>


<image
path = "186r.jpg"
thumbpath = "186r.jpg"
thumbwidth = "145"
</image>


<image
path = "186v.jpg"
thumbpath = "186v.jpg"
thumbwidth = "146"
</image>


<image
path = "187r.jpg"
thumbpath = "187r.jpg"
thumbwidth = "147"
</image>


<image
path = "187v.jpg"
thumbpath = "187v.jpg"
thumbwidth = "146"
</image>


<image
path = "188r.jpg"
thumbpath = "188r.jpg"
thumbwidth = "146"
</image>


<image
path = "188v.jpg"
thumbpath = "188v.jpg"
thumbwidth = "146"
</image>


<image
path = "189r.jpg"
thumbpath = "189r.jpg"
thumbwidth = "147"
</image>


<image
path = "189v.jpg"
thumbpath = "189v.jpg"
thumbwidth = "145"
</image>


<image
path = "190r.jpg"
thumbpath = "190r.jpg"
thumbwidth = "145"
</image>


<image
path = "190v.jpg"
thumbpath = "190v.jpg"
thumbwidth = "146"
</image>


<image
path = "191r.jpg"
thumbpath = "191r.jpg"
thumbwidth = "146"
</image>


<image
path = "191v.jpg"
thumbpath = "191v.jpg"
thumbwidth = "147"
</image>


<image
path = "192r.jpg"
thumbpath = "192r.jpg"
thumbwidth = "146"
</image>


<image
path = "192v.jpg"
thumbpath = "192v.jpg"
thumbwidth = "147"
</image>


<image
path = "193r.jpg"
thumbpath = "193r.jpg"
thumbwidth = "147"
</image>


<image
path = "193v.jpg"
thumbpath = "193v.jpg"
thumbwidth = "145"
</image>


<image
path = "194r.jpg"
thumbpath = "194r.jpg"
thumbwidth = "146"
</image>


<image
path = "194v.jpg"
thumbpath = "194v.jpg"
thumbwidth = "147"
</image>


<image
path = "195r.jpg"
thumbpath = "195r.jpg"
thumbwidth = "146"
</image>


<image
path = "195v.jpg"
thumbpath = "195v.jpg"
thumbwidth = "145"
</image>


<image
path = "196r.jpg"
thumbpath = "196r.jpg"
thumbwidth = "141"
</image>


<image
path = "196v.jpg"
thumbpath = "196v.jpg"
thumbwidth = "144"
</image>


<image
path = "197r.jpg"
thumbpath = "197r.jpg"
thumbwidth = "142"
</image>


<image
path = "197v.jpg"
thumbpath = "197v.jpg"
thumbwidth = "141"
</image>


<image
path = "198r.jpg"
thumbpath = "198r.jpg"
thumbwidth = "141"
</image>


<image
path = "198v.jpg"
thumbpath = "198v.jpg"
thumbwidth = "142"
</image>


<image
path = "199r.jpg"
thumbpath = "199r.jpg"
thumbwidth = "142"
</image>


<image
path = "199v.jpg"
thumbpath = "199v.jpg"
thumbwidth = "141"
</image>


<image
path = "200r.jpg"
thumbpath = "200r.jpg"
thumbwidth = "142"
</image>


<image
path = "200v.jpg"
thumbpath = "200v.jpg"
thumbwidth = "142"
</image>


<image
path = "201r.jpg"
thumbpath = "201r.jpg"
thumbwidth = "142"
</image>


<image
path = "201v.jpg"
thumbpath = "201v.jpg"
thumbwidth = "141"
</image>


<image
path = "202r.jpg"
thumbpath = "202r.jpg"
thumbwidth = "142"
</image>


<image
path = "202v.jpg"
thumbpath = "202v.jpg"
thumbwidth = "141"
</image>


<image
path = "203r.jpg"
thumbpath = "203r.jpg"
thumbwidth = "140"
</image>


<image
path = "203v.jpg"
thumbpath = "203v.jpg"
thumbwidth = "141"
</image>


<image
path = "204r.jpg"
thumbpath = "204r.jpg"
thumbwidth = "141"
</image>


<image
path = "204v.jpg"
thumbpath = "204v.jpg"
thumbwidth = "141"
</image>


<image
path = "205r.jpg"
thumbpath = "205r.jpg"
thumbwidth = "141"
</image>


<image
path = "205v.jpg"
thumbpath = "205v.jpg"
thumbwidth = "142"
</image>


<image
path = "206r.jpg"
thumbpath = "206r.jpg"
thumbwidth = "141"
</image>


<image
path = "206v.jpg"
thumbpath = "206v.jpg"
thumbwidth = "141"
</image>


<image
path = "207r.jpg"
thumbpath = "207r.jpg"
thumbwidth = "142"
</image>


<image
path = "207v.jpg"
thumbpath = "207v.jpg"
thumbwidth = "142"
</image>


<image
path = "208r.jpg"
thumbpath = "208r.jpg"
thumbwidth = "141"
</image>


<image
path = "208v.jpg"
thumbpath = "208v.jpg"
thumbwidth = "141"
</image>


<image
path = "209r.jpg"
thumbpath = "209r.jpg"
thumbwidth = "141"
</image>


<image
path = "209v.jpg"
thumbpath = "209v.jpg"
thumbwidth = "142"
</image>


<image
path = "210r.jpg"
thumbpath = "210r.jpg"
thumbwidth = "142"
</image>


<image
path = "210v.jpg"
thumbpath = "210v.jpg"
thumbwidth = "141"
</image>


<image
path = "211r.jpg"
thumbpath = "211r.jpg"
thumbwidth = "141"
</image>


<image
path = "211v.jpg"
thumbpath = "211v.jpg"
thumbwidth = "141"
</image>


<image
path = "212r.jpg"
thumbpath = "212r.jpg"
thumbwidth = "141"
</image>


<image
path = "212v.jpg"
thumbpath = "212v.jpg"
thumbwidth = "142"
</image>


<image
path = "213r.jpg"
thumbpath = "213r.jpg"
thumbwidth = "142"
</image>


<image
path = "213v.jpg"
thumbpath = "213v.jpg"
thumbwidth = "142"
</image>


<image
path = "214r.jpg"
thumbpath = "214r.jpg"
thumbwidth = "142"
</image>


<image
path = "214v.jpg"
thumbpath = "214v.jpg"
thumbwidth = "141"
</image>


<image
path = "215r.jpg"
thumbpath = "215r.jpg"
thumbwidth = "141"
</image>


<image
path = "215v.jpg"
thumbpath = "215v.jpg"
thumbwidth = "142"
</image>


<image
path = "216r.jpg"
thumbpath = "216r.jpg"
thumbwidth = "142"
</image>


<image
path = "216v.jpg"
thumbpath = "216v.jpg"
thumbwidth = "142"
</image>


<image
path = "217r.jpg"
thumbpath = "217r.jpg"
thumbwidth = "141"
</image>


<image
path = "217v.jpg"
thumbpath = "217v.jpg"
thumbwidth = "142"
</image>


<image
path = "218r.jpg"
thumbpath = "218r.jpg"
thumbwidth = "142"
</image>


<image
path = "218v.jpg"
thumbpath = "218v.jpg"
thumbwidth = "142"
</image>


<image
path = "219r.jpg"
thumbpath = "219r.jpg"
thumbwidth = "142"
</image>


<image
path = "219v.jpg"
thumbpath = "219v.jpg"
thumbwidth = "141"
</image>


<image
path = "220r.jpg"
thumbpath = "220r.jpg"
thumbwidth = "141"
</image>


<image
path = "220v.jpg"
thumbpath = "220v.jpg"
thumbwidth = "141"
</image>


<image
path = "221r.jpg"
thumbpath = "221r.jpg"
thumbwidth = "142"
</image>


<image
path = "221v.jpg"
thumbpath = "221v.jpg"
thumbwidth = "141"
</image>


<image
path = "222r.jpg"
thumbpath = "222r.jpg"
thumbwidth = "142"
</image>


<image
path = "222v.jpg"
thumbpath = "222v.jpg"
thumbwidth = "141"
</image>


<image
path = "223r.jpg"
thumbpath = "223r.jpg"
thumbwidth = "141"
</image>


<image
path = "223v.jpg"
thumbpath = "223v.jpg"
thumbwidth = "142"
</image>


<image
path = "224r.jpg"
thumbpath = "224r.jpg"
thumbwidth = "142"
</image>


<image
path = "224v.jpg"
thumbpath = "224v.jpg"
thumbwidth = "141"
</image>


<image
path = "225r.jpg"
thumbpath = "225r.jpg"
thumbwidth = "141"
</image>


<image
path = "225v.jpg"
thumbpath = "225v.jpg"
thumbwidth = "141"
</image>


<image
path = "226r.jpg"
thumbpath = "226r.jpg"
thumbwidth = "141"
</image>


<image
path = "226v.jpg"
thumbpath = "226v.jpg"
thumbwidth = "141"
</image>


<image
path = "227r.jpg"
thumbpath = "227r.jpg"
thumbwidth = "141"
</image>


<image
path = "227v.jpg"
thumbpath = "227v.jpg"
thumbwidth = "141"
</image>


<image
path = "228r.jpg"
thumbpath = "228r.jpg"
thumbwidth = "143"
</image>


<image
path = "228v.jpg"
thumbpath = "228v.jpg"
thumbwidth = "143"
</image>


<image
path = "229r.jpg"
thumbpath = "229r.jpg"
thumbwidth = "143"
</image>


<image
path = "229v.jpg"
thumbpath = "229v.jpg"
thumbwidth = "142"
</image>


<image
path = "230r.jpg"
thumbpath = "230r.jpg"
thumbwidth = "142"
</image>


<image
path = "230v.jpg"
thumbpath = "230v.jpg"
thumbwidth = "142"
</image>


<image
path = "231r.jpg"
thumbpath = "231r.jpg"
thumbwidth = "142"
</image>


<image
path = "231v.jpg"
thumbpath = "231v.jpg"
thumbwidth = "142"
</image>


<image
path = "232r.jpg"
thumbpath = "232r.jpg"
thumbwidth = "142"
</image>


<image
path = "232v.jpg"
thumbpath = "232v.jpg"
thumbwidth = "143"
</image>


<image
path = "233r.jpg"
thumbpath = "233r.jpg"
thumbwidth = "141"
</image>


<image
path = "233v.jpg"
thumbpath = "233v.jpg"
thumbwidth = "142"
</image>


<image
path = "234r.jpg"
thumbpath = "234r.jpg"
thumbwidth = "142"
</image>


<image
path = "234v.jpg"
thumbpath = "234v.jpg"
thumbwidth = "141"
</image>


<image
path = "235r.jpg"
thumbpath = "235r.jpg"
thumbwidth = "141"
</image>


<image
path = "235v.jpg"
thumbpath = "235v.jpg"
thumbwidth = "141"
</image>


<image
path = "236r.jpg"
thumbpath = "236r.jpg"
thumbwidth = "142"
</image>


<image
path = "236v.jpg"
thumbpath = "236v.jpg"
thumbwidth = "141"
</image>


<image
path = "237r.jpg"
thumbpath = "237r.jpg"
thumbwidth = "142"
</image>


<image
path = "237v.jpg"
thumbpath = "237v.jpg"
thumbwidth = "141"
</image>


<image
path = "238r.jpg"
thumbpath = "238r.jpg"
thumbwidth = "141"
</image>


<image
path = "238v.jpg"
thumbpath = "238v.jpg"
thumbwidth = "141"
</image>


<image
path = "239r.jpg"
thumbpath = "239r.jpg"
thumbwidth = "141"
</image>


<image
path = "239v.jpg"
thumbpath = "239v.jpg"
thumbwidth = "140"
</image>


<image
path = "240r.jpg"
thumbpath = "240r.jpg"
thumbwidth = "141"
</image>


<image
path = "240v.jpg"
thumbpath = "240v.jpg"
thumbwidth = "141"
</image>


<image
path = "241r.jpg"
thumbpath = "241r.jpg"
thumbwidth = "141"
</image>


<image
path = "241v.jpg"
thumbpath = "241v.jpg"
thumbwidth = "140"
</image>


<image
path = "242r.jpg"
thumbpath = "242r.jpg"
thumbwidth = "141"
</image>


<image
path = "242v.jpg"
thumbpath = "242v.jpg"
thumbwidth = "140"
</image>


<image
path = "243r.jpg"
thumbpath = "243r.jpg"
thumbwidth = "140"
</image>


<image
path = "243v.jpg"
thumbpath = "243v.jpg"
thumbwidth = "140"
</image>


<image
path = "244r.jpg"
thumbpath = "244r.jpg"
thumbwidth = "140"
</image>


<image
path = "244v.jpg"
thumbpath = "244v.jpg"
thumbwidth = "140"
</image>


<image
path = "245r.jpg"
thumbpath = "245r.jpg"
thumbwidth = "140"
</image>


<image
path = "245v.jpg"
thumbpath = "245v.jpg"
thumbwidth = "140"
</image>


<image
path = "246r.jpg"
thumbpath = "246r.jpg"
thumbwidth = "140"
</image>


<image
path = "246v.jpg"
thumbpath = "246v.jpg"
thumbwidth = "140"
</image>


<image
path = "247r.jpg"
thumbpath = "247r.jpg"
thumbwidth = "140"
</image>


<image
path = "247v.jpg"
thumbpath = "247v.jpg"
thumbwidth = "140"
</image>


<image
path = "248r.jpg"
thumbpath = "248r.jpg"
thumbwidth = "140"
</image>


<image
path = "248v.jpg"
thumbpath = "248v.jpg"
thumbwidth = "140"
</image>


<image
path = "249r.jpg"
thumbpath = "249r.jpg"
thumbwidth = "140"
</image>


<image
path = "249v.jpg"
thumbpath = "249v.jpg"
thumbwidth = "140"
</image>


<image
path = "250r.jpg"
thumbpath = "250r.jpg"
thumbwidth = "139"
</image>


<image
path = "250v.jpg"
thumbpath = "250v.jpg"
thumbwidth = "141"
</image>


<image
path = "251r.jpg"
thumbpath = "251r.jpg"
thumbwidth = "140"
</image>


<image
path = "251v.jpg"
thumbpath = "251v.jpg"
thumbwidth = "141"
</image>


<image
path = "252r.jpg"
thumbpath = "252r.jpg"
thumbwidth = "139"
</image>


<image
path = "252v.jpg"
thumbpath = "252v.jpg"
thumbwidth = "139"
</image>


<image
path = "253r.jpg"
thumbpath = "253r.jpg"
thumbwidth = "143"
</image>


<image
path = "253v.jpg"
thumbpath = "253v.jpg"
thumbwidth = "142"
</image>


<image
path = "254r.jpg"
thumbpath = "254r.jpg"
thumbwidth = "143"
</image>


<image
path = "254v.jpg"
thumbpath = "254v.jpg"
thumbwidth = "142"
</image>


<image
path = "255r.jpg"
thumbpath = "255r.jpg"
thumbwidth = "142"
</image>


<image
path = "255v.jpg"
thumbpath = "255v.jpg"
thumbwidth = "142"
</image>


<image
path = "256r.jpg"
thumbpath = "256r.jpg"
thumbwidth = "143"
</image>


<image
path = "256v.jpg"
thumbpath = "256v.jpg"
thumbwidth = "142"
</image>


<image
path = "257r.jpg"
thumbpath = "257r.jpg"
thumbwidth = "142"
</image>


<image
path = "257v.jpg"
thumbpath = "257v.jpg"
thumbwidth = "145"
</image>


<image
path = "258r.jpg"
thumbpath = "258r.jpg"
thumbwidth = "146"
</image>


<image
path = "258v.jpg"
thumbpath = "258v.jpg"
thumbwidth = "145"
</image>


<image
path = "259r.jpg"
thumbpath = "259r.jpg"
thumbwidth = "145"
</image>


<image
path = "259v.jpg"
thumbpath = "259v.jpg"
thumbwidth = "145"
</image>


<image
path = "260r.jpg"
thumbpath = "260r.jpg"
thumbwidth = "146"
</image>


<image
path = "260v.jpg"
thumbpath = "260v.jpg"
thumbwidth = "145"
</image>


<image
path = "261r.jpg"
thumbpath = "261r.jpg"
thumbwidth = "146"
</image>


<image
path = "261v.jpg"
thumbpath = "261v.jpg"
thumbwidth = "146"
</image>


<image
path = "262r.jpg"
thumbpath = "262r.jpg"
thumbwidth = "145"
</image>


<image
path = "262v.jpg"
thumbpath = "262v.jpg"
thumbwidth = "145"
</image>


<image
path = "263r.jpg"
thumbpath = "263r.jpg"
thumbwidth = "145"
</image>


<image
path = "263v.jpg"
thumbpath = "263v.jpg"
thumbwidth = "145"
</image>


<image
path = "264r.jpg"
thumbpath = "264r.jpg"
thumbwidth = "146"
</image>


<image
path = "264v.jpg"
thumbpath = "264v.jpg"
thumbwidth = "146"
</image>


<image
path = "265r.jpg"
thumbpath = "265r.jpg"
thumbwidth = "146"
</image>


<image
path = "265v.jpg"
thumbpath = "265v.jpg"
thumbwidth = "145"
</image>


<image
path = "266r.jpg"
thumbpath = "266r.jpg"
thumbwidth = "146"
</image>


<image
path = "266v.jpg"
thumbpath = "266v.jpg"
thumbwidth = "146"
</image>


<image
path = "267r.jpg"
thumbpath = "267r.jpg"
thumbwidth = "145"
</image>


<image
path = "267v.jpg"
thumbpath = "267v.jpg"
thumbwidth = "146"
</image>


<image
path = "268r.jpg"
thumbpath = "268r.jpg"
thumbwidth = "145"
</image>


<image
path = "268v.jpg"
thumbpath = "268v.jpg"
thumbwidth = "146"
</image>


<image
path = "269r.jpg"
thumbpath = "269r.jpg"
thumbwidth = "145"
</image>


<image
path = "269v.jpg"
thumbpath = "269v.jpg"
thumbwidth = "145"
</image>


<image
path = "270r.jpg"
thumbpath = "270r.jpg"
thumbwidth = "145"
</image>


<image
path = "270v.jpg"
thumbpath = "270v.jpg"
thumbwidth = "145"
</image>


<image
path = "271r.jpg"
thumbpath = "271r.jpg"
thumbwidth = "145"
</image>


<image
path = "271v.jpg"
thumbpath = "271v.jpg"
thumbwidth = "145"
</image>


<image
path = "272r.jpg"
thumbpath = "272r.jpg"
thumbwidth = "145"
</image>


<image
path = "272v.jpg"
thumbpath = "272v.jpg"
thumbwidth = "145"
</image>


<image
path = "273r.jpg"
thumbpath = "273r.jpg"
thumbwidth = "146"
</image>


<image
path = "273v.jpg"
thumbpath = "273v.jpg"
thumbwidth = "146"
</image>


<image
path = "274r.jpg"
thumbpath = "274r.jpg"
thumbwidth = "145"
</image>


<image
path = "274v.jpg"
thumbpath = "274v.jpg"
thumbwidth = "145"
</image>


<image
path = "275r.jpg"
thumbpath = "275r.jpg"
thumbwidth = "142"
</image>


<image
path = "275v.jpg"
thumbpath = "275v.jpg"
thumbwidth = "141"
</image>


<image
path = "276r.jpg"
thumbpath = "276r.jpg"
thumbwidth = "141"
</image>


<image
path = "276v.jpg"
thumbpath = "276v.jpg"
thumbwidth = "141"
</image>


<image
path = "277r.jpg"
thumbpath = "277r.jpg"
thumbwidth = "142"
</image>


<image
path = "277v.jpg"
thumbpath = "277v.jpg"
thumbwidth = "141"
</image>


<image
path = "278r.jpg"
thumbpath = "278r.jpg"
thumbwidth = "144"
</image>


<image
path = "278v.jpg"
thumbpath = "278v.jpg"
thumbwidth = "143"
</image>


<image
path = "279r.jpg"
thumbpath = "279r.jpg"
thumbwidth = "144"
</image>


<image
path = "279v.jpg"
thumbpath = "279v.jpg"
thumbwidth = "143"
</image>


<image
path = "280r.jpg"
thumbpath = "280r.jpg"
thumbwidth = "141"
</image>


<image
path = "280v.jpg"
thumbpath = "280v.jpg"
thumbwidth = "143"
</image>


<image
path = "281r.jpg"
thumbpath = "281r.jpg"
thumbwidth = "143"
</image>


<image
path = "281v.jpg"
thumbpath = "281v.jpg"
thumbwidth = "143"
</image>


<image
path = "282r.jpg"
thumbpath = "282r.jpg"
thumbwidth = "143"
</image>


<image
path = "282v.jpg"
thumbpath = "282v.jpg"
thumbwidth = "143"
</image>


<image
path = "283r.jpg"
thumbpath = "283r.jpg"
thumbwidth = "143"
</image>


<image
path = "283v.jpg"
thumbpath = "283v.jpg"
thumbwidth = "142"
</image>


<image
path = "284r.jpg"
thumbpath = "284r.jpg"
thumbwidth = "142"
</image>


<image
path = "284v.jpg"
thumbpath = "284v.jpg"
thumbwidth = "142"
</image>


<image
path = "285r.jpg"
thumbpath = "285r.jpg"
thumbwidth = "145"
</image>


<image
path = "285v.jpg"
thumbpath = "285v.jpg"
thumbwidth = "143"
</image>


<image
path = "286r.jpg"
thumbpath = "286r.jpg"
thumbwidth = "142"
</image>


<image
path = "286v.jpg"
thumbpath = "286v.jpg"
thumbwidth = "142"
</image>


<image
path = "287r.jpg"
thumbpath = "287r.jpg"
thumbwidth = "143"
</image>


<image
path = "287v.jpg"
thumbpath = "287v.jpg"
thumbwidth = "142"
</image>


<image
path = "288r.jpg"
thumbpath = "288r.jpg"
thumbwidth = "142"
</image>


<image
path = "288v.jpg"
thumbpath = "288v.jpg"
thumbwidth = "142"
</image>


<image
path = "289r.jpg"
thumbpath = "289r.jpg"
thumbwidth = "142"
</image>


<image
path = "289v.jpg"
thumbpath = "289v.jpg"
thumbwidth = "142"
</image>


<image
path = "290r.jpg"
thumbpath = "290r.jpg"
thumbwidth = "142"
</image>


<image
path = "290v.jpg"
thumbpath = "290v.jpg"
thumbwidth = "142"
</image>


<image
path = "291r.jpg"
thumbpath = "291r.jpg"
thumbwidth = "143"
</image>


<image
path = "291v.jpg"
thumbpath = "291v.jpg"
thumbwidth = "142"
</image>


<image
path = "292r.jpg"
thumbpath = "292r.jpg"
thumbwidth = "143"
</image>


<image
path = "292v.jpg"
thumbpath = "292v.jpg"
thumbwidth = "143"
</image>


<image
path = "293r.jpg"
thumbpath = "293r.jpg"
thumbwidth = "142"
</image>


<image
path = "293v.jpg"
thumbpath = "293v.jpg"
thumbwidth = "143"
</image>


<image
path = "294r.jpg"
thumbpath = "294r.jpg"
thumbwidth = "142"
</image>


<image
path = "294v.jpg"
thumbpath = "294v.jpg"
thumbwidth = "143"
</image>


<image
path = "295r.jpg"
thumbpath = "295r.jpg"
thumbwidth = "142"
</image>


<image
path = "295v.jpg"
thumbpath = "295v.jpg"
thumbwidth = "143"
</image>


<image
path = "296r.jpg"
thumbpath = "296r.jpg"
thumbwidth = "141"
</image>


<image
path = "296v.jpg"
thumbpath = "296v.jpg"
thumbwidth = "143"
</image>


<image
path = "297r.jpg"
thumbpath = "297r.jpg"
thumbwidth = "141"
</image>


<image
path = "297v.jpg"
thumbpath = "297v.jpg"
thumbwidth = "142"
</image>


<image
path = "298r.jpg"
thumbpath = "298r.jpg"
thumbwidth = "142"
</image>


<image
path = "298v.jpg"
thumbpath = "298v.jpg"
thumbwidth = "141"
</image>


<image
path = "299r.jpg"
thumbpath = "299r.jpg"
thumbwidth = "141"
</image>


<image
path = "299v.jpg"
thumbpath = "299v.jpg"
thumbwidth = "141"
</image>


<image
path = "300r.jpg"
thumbpath = "300r.jpg"
thumbwidth = "142"
</image>


<image
path = "300v.jpg"
thumbpath = "300v.jpg"
thumbwidth = "142"
</image>


<image
path = "301r.jpg"
thumbpath = "301r.jpg"
thumbwidth = "142"
</image>


<image
path = "301v.jpg"
thumbpath = "301v.jpg"
thumbwidth = "142"
</image>


<image
path = "302r.jpg"
thumbpath = "302r.jpg"
thumbwidth = "142"
</image>


<image
path = "302v.jpg"
thumbpath = "302v.jpg"
thumbwidth = "141"
</image>


<image
path = "303r.jpg"
thumbpath = "303r.jpg"
thumbwidth = "144"
</image>


<image
path = "303v.jpg"
thumbpath = "303v.jpg"
thumbwidth = "143"
</image>


<image
path = "304r.jpg"
thumbpath = "304r.jpg"
thumbwidth = "143"
</image>


<image
path = "304v.jpg"
thumbpath = "304v.jpg"
thumbwidth = "143"
</image>


<image
path = "305r.jpg"
thumbpath = "305r.jpg"
thumbwidth = "144"
</image>


<image
path = "305v.jpg"
thumbpath = "305v.jpg"
thumbwidth = "143"
</image>


<image
path = "306r.jpg"
thumbpath = "306r.jpg"
thumbwidth = "145"
</image>


<image
path = "306v.jpg"
thumbpath = "306v.jpg"
thumbwidth = "143"
</image>


<image
path = "307r.jpg"
thumbpath = "307r.jpg"
thumbwidth = "144"
</image>


<image
path = "307v.jpg"
thumbpath = "307v.jpg"
thumbwidth = "143"
</image>


<image
path = "308r.jpg"
thumbpath = "308r.jpg"
thumbwidth = "143"
</image>


<image
path = "308v.jpg"
thumbpath = "308v.jpg"
thumbwidth = "143"
</image>


<image
path = "309r.jpg"
thumbpath = "309r.jpg"
thumbwidth = "144"
</image>


<image
path = "309v.jpg"
thumbpath = "309v.jpg"
thumbwidth = "143"
</image>


<image
path = "310r.jpg"
thumbpath = "310r.jpg"
thumbwidth = "144"
</image>


<image
path = "310v.jpg"
thumbpath = "310v.jpg"
thumbwidth = "143"
</image>


<image
path = "311r.jpg"
thumbpath = "311r.jpg"
thumbwidth = "144"
</image>


<image
path = "311v.jpg"
thumbpath = "311v.jpg"
thumbwidth = "143"
</image>


<image
path = "312r.jpg"
thumbpath = "312r.jpg"
thumbwidth = "143"
</image>


<image
path = "312v.jpg"
thumbpath = "312v.jpg"
thumbwidth = "143"
</image>


<image
path = "313r.jpg"
thumbpath = "313r.jpg"
thumbwidth = "143"
</image>


<image
path = "313v.jpg"
thumbpath = "313v.jpg"
thumbwidth = "143"
</image>


<image
path = "314r.jpg"
thumbpath = "314r.jpg"
thumbwidth = "144"
</image>


<image
path = "314v.jpg"
thumbpath = "314v.jpg"
thumbwidth = "143"
</image>


<image
path = "315r.jpg"
thumbpath = "315r.jpg"
thumbwidth = "143"
</image>


<image
path = "315v.jpg"
thumbpath = "315v.jpg"
thumbwidth = "143"
</image>


<image
path = "316r.jpg"
thumbpath = "316r.jpg"
thumbwidth = "143"
</image>


<image
path = "316v.jpg"
thumbpath = "316v.jpg"
thumbwidth = "143"
</image>


<image
path = "317r.jpg"
thumbpath = "317r.jpg"
thumbwidth = "143"
</image>


<image
path = "317v.jpg"
thumbpath = "317v.jpg"
thumbwidth = "144"
</image>


<image
path = "318r.jpg"
thumbpath = "318r.jpg"
thumbwidth = "143"
</image>


<image
path = "318v.jpg"
thumbpath = "318v.jpg"
thumbwidth = "143"
</image>


<image
path = "319r.jpg"
thumbpath = "319r.jpg"
thumbwidth = "143"
</image>


<image
path = "319v.jpg"
thumbpath = "319v.jpg"
thumbwidth = "143"
</image>


<image
path = "320r.jpg"
thumbpath = "320r.jpg"
thumbwidth = "143"
</image>


<image
path = "320v.jpg"
thumbpath = "320v.jpg"
thumbwidth = "143"
</image>


<image
path = "321r.jpg"
thumbpath = "321r.jpg"
thumbwidth = "143"
</image>


<image
path = "321v.jpg"
thumbpath = "321v.jpg"
thumbwidth = "143"
</image>


<image
path = "322r.jpg"
thumbpath = "322r.jpg"
thumbwidth = "143"
</image>


<image
path = "322v.jpg"
thumbpath = "322v.jpg"
thumbwidth = "143"
</image>


<image
path = "323r.jpg"
thumbpath = "323r.jpg"
thumbwidth = "143"
</image>


<image
path = "323v.jpg"
thumbpath = "323v.jpg"
thumbwidth = "143"
</image>


<image
path = "324r.jpg"
thumbpath = "324r.jpg"
thumbwidth = "143"
</image>


<image
path = "324v.jpg"
thumbpath = "324v.jpg"
thumbwidth = "143"
</image>


<image
path = "325r.jpg"
thumbpath = "325r.jpg"
thumbwidth = "141"
</image>


<image
path = "325v.jpg"
thumbpath = "325v.jpg"
thumbwidth = "143"
</image>


<image
path = "326r.jpg"
thumbpath = "326r.jpg"
thumbwidth = "143"
</image>


<image
path = "326v.jpg"
thumbpath = "326v.jpg"
thumbwidth = "143"
</image>


<image
path = "327r.jpg"
thumbpath = "327r.jpg"
thumbwidth = "144"
</image>


<image
path = "327v.jpg"
thumbpath = "327v.jpg"
thumbwidth = "144"
</image>


<image
path = "328r.jpg"
thumbpath = "328r.jpg"
thumbwidth = "142"
</image>


<image
path = "328v.jpg"
thumbpath = "328v.jpg"
thumbwidth = "142"
</image>


<image
path = "329r.jpg"
thumbpath = "329r.jpg"
thumbwidth = "142"
</image>


<image
path = "329v.jpg"
thumbpath = "329v.jpg"
thumbwidth = "141"
</image>


<image
path = "330r.jpg"
thumbpath = "330r.jpg"
thumbwidth = "142"
</image>


<image
path = "330v.jpg"
thumbpath = "330v.jpg"
thumbwidth = "142"
</image>


<image
path = "331r.jpg"
thumbpath = "331r.jpg"
thumbwidth = "142"
</image>


<image
path = "331v.jpg"
thumbpath = "331v.jpg"
thumbwidth = "142"
</image>


<image
path = "332r.jpg"
thumbpath = "332r.jpg"
thumbwidth = "142"
</image>


<image
path = "332v.jpg"
thumbpath = "332v.jpg"
thumbwidth = "142"
</image>


<image
path = "333r.jpg"
thumbpath = "333r.jpg"
thumbwidth = "142"
</image>


<image
path = "333v.jpg"
thumbpath = "333v.jpg"
thumbwidth = "142"
</image>


<image
path = "334r.jpg"
thumbpath = "334r.jpg"
thumbwidth = "139"
</image>


<image
path = "334v.jpg"
thumbpath = "334v.jpg"
thumbwidth = "138"
</image>


<image
path = "335r.jpg"
thumbpath = "335r.jpg"
thumbwidth = "143"
</image>


<image
path = "335v.jpg"
thumbpath = "335v.jpg"
thumbwidth = "149"
</image>


<image
path = "336r.jpg"
thumbpath = "336r.jpg"
thumbwidth = "142"
</image>


<image
path = "336v.jpg"
thumbpath = "336v.jpg"
thumbwidth = "142"
</image>


<image
path = "337r.jpg"
thumbpath = "337r.jpg"
thumbwidth = "146"
</image>


<image
path = "337v.jpg"
thumbpath = "337v.jpg"
thumbwidth = "146"
</image>


<image
path = "338r.jpg"
thumbpath = "338r.jpg"
thumbwidth = "146"
</image>


<image
path = "338v.jpg"
thumbpath = "338v.jpg"
thumbwidth = "146"
</image>


<image
path = "339r.jpg"
thumbpath = "339r.jpg"
thumbwidth = "146"
</image>


<image
path = "339v.jpg"
thumbpath = "339v.jpg"
thumbwidth = "146"
</image>


<image
path = "340r.jpg"
thumbpath = "340r.jpg"
thumbwidth = "146"
</image>


<image
path = "340v.jpg"
thumbpath = "340v.jpg"
thumbwidth = "146"
</image>


<image
path = "341r.jpg"
thumbpath = "341r.jpg"
thumbwidth = "146"
</image>


<image
path = "341v.jpg"
thumbpath = "341v.jpg"
thumbwidth = "146"
</image>


<image
path = "342r.jpg"
thumbpath = "342r.jpg"
thumbwidth = "146"
</image>


<image
path = "342v.jpg"
thumbpath = "342v.jpg"
thumbwidth = "146"
</image>


<image
path = "343r.jpg"
thumbpath = "343r.jpg"
thumbwidth = "146"
</image>


<image
path = "343v.jpg"
thumbpath = "343v.jpg"
thumbwidth = "146"
</image>


<image
path = "344r.jpg"
thumbpath = "344r.jpg"
thumbwidth = "146"
</image>


<image
path = "344v.jpg"
thumbpath = "344v.jpg"
thumbwidth = "146"
</image>


<image
path = "345r.jpg"
thumbpath = "345r.jpg"
thumbwidth = "146"
</image>


<image
path = "345v.jpg"
thumbpath = "345v.jpg"
thumbwidth = "146"
</image>


<image
path = "346r.jpg"
thumbpath = "346r.jpg"
thumbwidth = "144"
</image>


<image
path = "346v.jpg"
thumbpath = "346v.jpg"
thumbwidth = "144"
</image>


<image
path = "347r.jpg"
thumbpath = "347r.jpg"
thumbwidth = "144"
</image>


<image
path = "347v.jpg"
thumbpath = "347v.jpg"
thumbwidth = "144"
</image>


<image
path = "348r.jpg"
thumbpath = "348r.jpg"
thumbwidth = "144"
</image>


<image
path = "348v.jpg"
thumbpath = "348v.jpg"
thumbwidth = "144"
</image>


<image
path = "349r.jpg"
thumbpath = "349r.jpg"
thumbwidth = "140"
</image>


<image
path = "349v.jpg"
thumbpath = "349v.jpg"
thumbwidth = "144"
</image>


<image
path = "350r.jpg"
thumbpath = "350r.jpg"
thumbwidth = "144"
</image>


<image
path = "350v.jpg"
thumbpath = "350v.jpg"
thumbwidth = "145"
</image>


<image
path = "351r.jpg"
thumbpath = "351r.jpg"
thumbwidth = "145"
</image>


<image
path = "351v.jpg"
thumbpath = "351v.jpg"
thumbwidth = "145"
</image>


<image
path = "352r.jpg"
thumbpath = "352r.jpg"
thumbwidth = "145"
</image>


<image
path = "352v.jpg"
thumbpath = "352v.jpg"
thumbwidth = "145"
</image>


<image
path = "353r.jpg"
thumbpath = "353r.jpg"
thumbwidth = "142"
</image>


<image
path = "353v.jpg"
thumbpath = "353v.jpg"
thumbwidth = "142"
</image>


<image
path = "354r.jpg"
thumbpath = "354r.jpg"
thumbwidth = "140"
</image>


<image
path = "354v.jpg"
thumbpath = "354v.jpg"
thumbwidth = "142"
</image>


<image
path = "355r.jpg"
thumbpath = "355r.jpg"
thumbwidth = "141"
</image>


<image
path = "355v.jpg"
thumbpath = "355v.jpg"
thumbwidth = "142"
</image>


<image
path = "356r.jpg"
thumbpath = "356r.jpg"
thumbwidth = "140"
</image>


<image
path = "356v.jpg"
thumbpath = "356v.jpg"
thumbwidth = "142"
</image>


<image
path = "357r.jpg"
thumbpath = "357r.jpg"
thumbwidth = "140"
</image>


<image
path = "357v.jpg"
thumbpath = "357v.jpg"
thumbwidth = "142"
</image>


<image
path = "358r.jpg"
thumbpath = "358r.jpg"
thumbwidth = "142"
</image>


<image
path = "358v.jpg"
thumbpath = "358v.jpg"
thumbwidth = "142"
</image>


<image
path = "359r.jpg"
thumbpath = "359r.jpg"
thumbwidth = "142"
</image>


<image
path = "359v.jpg"
thumbpath = "359v.jpg"
thumbwidth = "142"
</image>


<image
path = "360r.jpg"
thumbpath = "360r.jpg"
thumbwidth = "141"
</image>


<image
path = "360v.jpg"
thumbpath = "360v.jpg"
thumbwidth = "142"
</image>


<image
path = "361r.jpg"
thumbpath = "361r.jpg"
thumbwidth = "142"
</image>


<image
path = "361v.jpg"
thumbpath = "361v.jpg"
thumbwidth = "142"
</image>


<image
path = "362r.jpg"
thumbpath = "362r.jpg"
thumbwidth = "142"
</image>


<image
path = "362v.jpg"
thumbpath = "362v.jpg"
thumbwidth = "142"
</image>


<image
path = "363r.jpg"
thumbpath = "363r.jpg"
thumbwidth = "142"
</image>


<image
path = "363v.jpg"
thumbpath = "363v.jpg"
thumbwidth = "142"
</image>


<image
path = "364r.jpg"
thumbpath = "364r.jpg"
thumbwidth = "142"
</image>


<image
path = "364v.jpg"
thumbpath = "364v.jpg"
thumbwidth = "142"
</image>


<image
path = "365r.jpg"
thumbpath = "365r.jpg"
thumbwidth = "141"
</image>


<image
path = "365v.jpg"
thumbpath = "365v.jpg"
thumbwidth = "142"
</image>


<image
path = "366r.jpg"
thumbpath = "366r.jpg"
thumbwidth = "142"
</image>


<image
path = "366v.jpg"
thumbpath = "366v.jpg"
thumbwidth = "142"
</image>


<image
path = "367r.jpg"
thumbpath = "367r.jpg"
thumbwidth = "142"
</image>


<image
path = "367v.jpg"
thumbpath = "367v.jpg"
thumbwidth = "143"
</image>


<image
path = "368r.jpg"
thumbpath = "368r.jpg"
thumbwidth = "143"
</image>


<image
path = "368v.jpg"
thumbpath = "368v.jpg"
thumbwidth = "143"
</image>


<image
path = "369r.jpg"
thumbpath = "369r.jpg"
thumbwidth = "143"
</image>


<image
path = "369v.jpg"
thumbpath = "369v.jpg"
thumbwidth = "143"
</image>


<image
path = "370r.jpg"
thumbpath = "370r.jpg"
thumbwidth = "143"
</image>


<image
path = "370v.jpg"
thumbpath = "370v.jpg"
thumbwidth = "143"
</image>


<image
path = "371r.jpg"
thumbpath = "371r.jpg"
thumbwidth = "143"
</image>


<image
path = "371v.jpg"
thumbpath = "371v.jpg"
thumbwidth = "143"
</image>


<image
path = "372r.jpg"
thumbpath = "372r.jpg"
thumbwidth = "143"
</image>


<image
path = "372v.jpg"
thumbpath = "372v.jpg"
thumbwidth = "143"
</image>


<image
path = "373r.jpg"
thumbpath = "373r.jpg"
thumbwidth = "143"
</image>


<image
path = "373v.jpg"
thumbpath = "373v.jpg"
thumbwidth = "143"
</image>


<image
path = "374r.jpg"
thumbpath = "374r.jpg"
thumbwidth = "143"
</image>


<image
path = "374v.jpg"
thumbpath = "374v.jpg"
thumbwidth = "143"
</image>


<image
path = "375r.jpg"
thumbpath = "375r.jpg"
thumbwidth = "144"
</image>


<image
path = "375v.jpg"
thumbpath = "375v.jpg"
thumbwidth = "145"
</image>


<image
path = "376r.jpg"
thumbpath = "376r.jpg"
thumbwidth = "145"
</image>


<image
path = "376v.jpg"
thumbpath = "376v.jpg"
thumbwidth = "145"
</image>


<image
path = "377r.jpg"
thumbpath = "377r.jpg"
thumbwidth = "144"
</image>


<image
path = "377v.jpg"
thumbpath = "377v.jpg"
thumbwidth = "145"
</image>


<image
path = "378r.jpg"
thumbpath = "378r.jpg"
thumbwidth = "145"
</image>


<image
path = "378v.jpg"
thumbpath = "378v.jpg"
thumbwidth = "145"
</image>


<image
path = "379r.jpg"
thumbpath = "379r.jpg"
thumbwidth = "145"
</image>


<image
path = "379v.jpg"
thumbpath = "379v.jpg"
thumbwidth = "145"
</image>


<image
path = "380r.jpg"
thumbpath = "380r.jpg"
thumbwidth = "145"
</image>


<image
path = "380v.jpg"
thumbpath = "380v.jpg"
thumbwidth = "145"
</image>


<image
path = "381r.jpg"
thumbpath = "381r.jpg"
thumbwidth = "145"
</image>


<image
path = "381v.jpg"
thumbpath = "381v.jpg"
thumbwidth = "145"
</image>


<image
path = "382r.jpg"
thumbpath = "382r.jpg"
thumbwidth = "145"
</image>


<image
path = "382v.jpg"
thumbpath = "382v.jpg"
thumbwidth = "145"
</image>


<image
path = "383r.jpg"
thumbpath = "383r.jpg"
thumbwidth = "145"
</image>


<image
path = "383v.jpg"
thumbpath = "383v.jpg"
thumbwidth = "145"
</image>


<image
path = "384r.jpg"
thumbpath = "384r.jpg"
thumbwidth = "145"
</image>


<image
path = "384v.jpg"
thumbpath = "384v.jpg"
thumbwidth = "141"
</image>


<image
path = "385r.jpg"
thumbpath = "385r.jpg"
thumbwidth = "142"
</image>


<image
path = "385v.jpg"
thumbpath = "385v.jpg"
thumbwidth = "141"
</image>


<image
path = "386r.jpg"
thumbpath = "386r.jpg"
thumbwidth = "141"
</image>


<image
path = "386v.jpg"
thumbpath = "386v.jpg"
thumbwidth = "141"
</image>


<image
path = "387r.jpg"
thumbpath = "387r.jpg"
thumbwidth = "141"
</image>


<image
path = "387v.jpg"
thumbpath = "387v.jpg"
thumbwidth = "141"
</image>


<image
path = "388r.jpg"
thumbpath = "388r.jpg"
thumbwidth = "142"
</image>


<image
path = "388v.jpg"
thumbpath = "388v.jpg"
thumbwidth = "141"
</image>


<image
path = "389r.jpg"
thumbpath = "389r.jpg"
thumbwidth = "142"
</image>


<image
path = "389v.jpg"
thumbpath = "389v.jpg"
thumbwidth = "141"
</image>


<image
path = "390r.jpg"
thumbpath = "390r.jpg"
thumbwidth = "141"
</image>


<image
path = "390v.jpg"
thumbpath = "390v.jpg"
thumbwidth = "142"
</image>


<image
path = "391r.jpg"
thumbpath = "391r.jpg"
thumbwidth = "141"
</image>


<image
path = "391v.jpg"
thumbpath = "391v.jpg"
thumbwidth = "141"
</image>


<image
path = "392r.jpg"
thumbpath = "392r.jpg"
thumbwidth = "142"
</image>


<image
path = "392v.jpg"
thumbpath = "392v.jpg"
thumbwidth = "141"
</image>


<image
path = "393r.jpg"
thumbpath = "393r.jpg"
thumbwidth = "142"
</image>


<image
path = "393v.jpg"
thumbpath = "393v.jpg"
thumbwidth = "145"
</image>


<image
path = "394r.jpg"
thumbpath = "394r.jpg"
thumbwidth = "145"
</image>


<image
path = "394v.jpg"
thumbpath = "394v.jpg"
thumbwidth = "146"
</image>


<image
path = "395r.jpg"
thumbpath = "395r.jpg"
thumbwidth = "145"
</image>


<image
path = "395v.jpg"
thumbpath = "395v.jpg"
thumbwidth = "145"
</image>


<image
path = "396r.jpg"
thumbpath = "396r.jpg"
thumbwidth = "145"
</image>


<image
path = "396v.jpg"
thumbpath = "396v.jpg"
thumbwidth = "145"
</image>


<image
path = "397r.jpg"
thumbpath = "397r.jpg"
thumbwidth = "145"
</image>


<image
path = "397v.jpg"
thumbpath = "397v.jpg"
thumbwidth = "145"
</image>


<image
path = "398r.jpg"
thumbpath = "398r.jpg"
thumbwidth = "145"
</image>


<image
path = "398v.jpg"
thumbpath = "398v.jpg"
thumbwidth = "145"
</image>


<image
path = "399r.jpg"
thumbpath = "399r.jpg"
thumbwidth = "145"
</image>


<image
path = "399v.jpg"
thumbpath = "399v.jpg"
thumbwidth = "145"
</image>

</images>
</gallery>
